kronos/__init__.py
kronos/helpers.py
kronos/job_manager.py
kronos/kronos.py
kronos/kronos_version.py
kronos/kronosui.py
kronos/logger.py
kronos/pipelineui.py
kronos/plumber.py
kronos/run_manager.py
kronos/utils.py
kronos/workflow_manager.py
kronos_pipeliner-2.3.0.dist-info/DESCRIPTION.rst
kronos_pipeliner-2.3.0.dist-info/entry_points.txt
kronos_pipeliner-2.3.0.dist-info/METADATA
kronos_pipeliner-2.3.0.dist-info/metadata.json
kronos_pipeliner-2.3.0.dist-info/RECORD
kronos_pipeliner-2.3.0.dist-info/top_level.txt
kronos_pipeliner-2.3.0.dist-info/WHEEL
templates/component_main.py
templates/component_params.py
templates/component_reqs.py
templates/component_ui.py
