Metadata-Version: 2.0
Name: kronos-pipeliner
Version: 2.3.0
Summary: A workflow assembler for genome analytics and informatics
Home-page: https://github.com/jtaghiyar/kronos
Author: M. Jafar Taghiyar
Author-email: jafar.taghiyar@gmail.com
License: MIT
Keywords: pipeline workflow bioinformatics kronos
Platform: UNKNOWN
Classifier: Development Status :: 5 - Production/Stable
Classifier: Intended Audience :: Science/Research
Classifier: Intended Audience :: Developers
Classifier: License :: OSI Approved :: MIT License
Classifier: Programming Language :: Python :: 2.7
Classifier: Topic :: Scientific/Engineering :: Bio-Informatics
Requires-Dist: pyyaml (>=3.11)
Requires-Dist: ruffus (==2.4.1)
